tensorboard_wrapper/__init__.py
tensorboard_wrapper/exceptions.py
tensorboard_wrapper/tensorboard.py
tensorboard_wrapper-0.2.1.dist-info/LICENSE
tensorboard_wrapper-0.2.1.dist-info/METADATA
tensorboard_wrapper-0.2.1.dist-info/WHEEL
tensorboard_wrapper-0.2.1.dist-info/top_level.txt
tensorboard_wrapper-0.2.1.dist-info/RECORD
