Metadata-Version: 2.1
Name: tensorboard-wrapper
Version: 0.2.1
Summary: Wrapper for Tensorflow's TensorBoard
Home-page: https://github.com/NathanGavenski/Tensorboard-Wrapper
Author: Nathan Gavenski
Author-email: nathangavenski@gmail.com
Classifier: Programming Language :: Python :: 3
Classifier: License :: OSI Approved :: MIT License
Classifier: Operating System :: OS Independent
Requires-Python: >=3.9
License-File: LICENSE
Requires-Dist: numpy
Requires-Dist: tensorboard
